nahuatl_tools/__init__.py
nahuatl_tools/analyze.py
nahuatl_tools/gloss.py
nahuatl_tools/orthography_converter.py
nahuatl_tools/parse.py
nahuatl_tools/pos_tagger.py
nahuatl_tools/tokenizer.py
nahuatl_tools-0.0.2.dist-info/LICENSE
nahuatl_tools-0.0.2.dist-info/METADATA
nahuatl_tools-0.0.2.dist-info/WHEEL
nahuatl_tools-0.0.2.dist-info/top_level.txt
nahuatl_tools-0.0.2.dist-info/RECORD
