Metadata-Version: 2.1
Name: nahuatl_tools
Version: 0.0.2
Summary: A selection of open source tools for Nahuatl NLP.
Author-email: Nicolas Cloutier <nicocloutier1@gmail.com>
Project-URL: Homepage, https://github.com/NicoACloutier/nahuatl_tools/tree/main
Classifier: Programming Language :: Python :: 3
Classifier: License :: OSI Approved :: MIT License
Classifier: Operating System :: OS Independent
Requires-Python: >=3.8
License-File: LICENSE
